extractor/__init__.py
extractor/admin.py
extractor/apps.py
extractor/models.py
extractor/tests.py
extractor/views.py
extractor/migrations/__init__.py
generator/__init__.py
generator/admin.py
generator/apps.py
generator/models.py
generator/tests.py
generator/views.py
generator/migrations/__init__.py
parser/__init__.py
parser/admin.py
parser/apps.py
parser/models.py
parser/tests.py
parser/views.py
parser/migrations/__init__.py
ssis_to_adf/__init__.py
ssis_to_adf/asgi.py
ssis_to_adf/settings.py
ssis_to_adf/urls.py
ssis_to_adf/wsgi.py
ssis_to_adf-1.0.dist-info/METADATA
ssis_to_adf-1.0.dist-info/WHEEL
ssis_to_adf-1.0.dist-info/top_level.txt
ssis_to_adf-1.0.dist-info/RECORD
